{
  "required": true,
  "minVersion": "0.8",
  "package": "cn.ksmcbrigade.ga.mixin",
  "compatibilityLevel": "JAVA_17",
  "refmap": "ga.refmap.json",
  "mixins": [
    "CameraSetupEventMixin",
    "ConnectionMixin",
    "LivingEntityAimMixin",
    "LivingEntityMeleeMixin",
    "LivingEntityShootMixin",
    "LivingEntitySprintMixin",
    "LocalPlayerSprintMixin",
    "ModernKineticGunScriptAPIMixin"
  ],
  "client": [
    "GunItemDataMixin2",
    "LocalPlayerShootMixin",
    "RenderSystemMixin"
  ],
  "injectors": {
    "defaultRequire": 1
  }
}
